fsspec_dnanexus/__init__.py
fsspec_dnanexus/core.py
fsspec_dnanexus/utils.py
fsspec_dnanexus/factories/__init__.py
fsspec_dnanexus/factories/dxdispatchers.py
fsspec_dnanexus/factories/dxfactory.py
fsspec_dnanexus/factories/dxpandas_on_python.py
fsspec_dnanexus/factories/dxpandas_on_ray.py
fsspec_dnanexus-0.2.7.dist-info/licenses/LICENSE.txt
fsspec_dnanexus-0.2.7.dist-info/METADATA
fsspec_dnanexus-0.2.7.dist-info/WHEEL
fsspec_dnanexus-0.2.7.dist-info/entry_points.txt
fsspec_dnanexus-0.2.7.dist-info/top_level.txt
fsspec_dnanexus-0.2.7.dist-info/RECORD
